{
  "languagePage": {
    "englishRadioButton": "#languageCode_en",
    "nextButton": "input#submit.button-continue"
  },
  "countrySelectPage": {
    "countryInput": "#countryCode_ui",
    "countrySuggestion": ".ui-autocomplete .ui-menu-item", 
    "nextButton": "input#submit.button-continue"
  },
  "vacConfirmationPage": {
    "confirmTrueRadioButton": "#vacAvailabilityConfirmed_true",
    "nextButton": "input#submit.button-continue"
  },
  "startApplicationPage": {
    "startButton": "#submit" 
  },
  "accountSetupPage": {
    "emailInput": "#email",
    "passwordInput_1": "#password1",
    "passwordInput_2": "#password2",
    "saveButton": "input#submit.button-continue"
  },
  "emailOwnerPage": {
    "isMyEmailRadioButton": "#emailOwner_you",
    "saveButton": "input#submit.button-continue"
  },
  "additionalEmailPage": {
    "noAdditionalEmailRadioButton": "#value_false",
    "saveButton": "input#submit.button-continue"
  },
  "telephonePage": {
    "telephoneInput": "#telephoneNumber",
    "purposeOutsideUKCheckbox": "#telephoneNumberPurpose_outsideUK",
    "typeMobileCheckbox": "#telephoneNumberType_mobile",
    "saveButton": "input#submit.button-continue"
  },
  "addAnotherTelephonePage": {
    "noRadioButton": "#addAnother_false",
    "saveButton": "input#submit.button-continue"
  },
  "contactPreferencePage": {
    "callAndTextRadioButton": "#contactByTelephone_callAndText",
    "saveButton": "input#submit.button-continue"
  },
  "namePage": {
    "givenNameInput": "#givenName",
    "familyNameInput": "#familyName",
    "saveButton": "input#submit.button-continue"
  },
  "otherNamesPage": {
    "noRadioButton": "#addAnother_false",
    "saveButton": "input#submit.button-continue"
  },
  "personalDetailsPage": {
    "genderMaleRadioButton": "#gender_1",
    "genderFemaleRadioButton": "#gender_2",
    "relationshipStatusSelect": "#relationshipStatus",
    "saveButton": "input#submit.button-continue"
  },
  "addressPage": {
    "addressLine1Input": "#outOfCountryAddress_line1",
    "townCityInput": "#outOfCountryAddress_townCity",
    "countryInput": "#outOfCountryAddress_countryRef_ui",
    "correspondenceAddressYes": "#isCorrespondenceAddress_true", 
    "saveButton": "input#submit.button-continue"
  },
  "livingSituationPage": {
"yearsLivedInput": "#yearsLived", 
  "monthsLivedInput": "#monthsLived",
    "ownershipOwnRadioButton": "#ownershipCategory_own",
    "ownershipRentRadioButton": "#ownershipCategory_rent",
    "ownershipOtherRadioButton": "#ownershipCategory_other",
    "otherOwnershipDetailsTextarea": "#otherCategoryDetails",
    "saveButton": "input#submit.button-continue"
  },
  "previousAddressPage": {
    "notInUkRadioButton": "#isUkAddress_false",
    "addressLine1Input": "#overseasAddress_line1",
    "townCityInput": "#overseasAddress_townCity",
    "countrySelect": "#overseasAddress_countryRef", 
    "startDateMonthInput": "#startDateAtAddress_month",
    "startDateYearInput": "#startDateAtAddress_year",
    "endDateMonthInput": "#endDateAtAddress_month",
    "endDateYearInput": "#endDateAtAddress_year",
    "saveButton": "input#submit.button-continue"
  },
  "addAnotherAddressPage": {
    "noRadioButton": "#addAnother_false",
    "saveButton": "input#submit.button-continue"
  },
  "passportDetailsPage": {
    "passportNumberInput": "#travelDocumentNumber",
    "issuingCountryInput": "#issuingCountry",
    "issueDayInput": "#dateOfIssue_day",
    "issueMonthInput": "#dateOfIssue_month",
    "issueYearInput": "#dateOfIssue_year",
    "expiryDayInput": "#expiryDate_day",
    "expiryMonthInput": "#expiryDate_month",
    "expiryYearInput": "#expiryDate_year",
    "saveButton": "input#submit.button-continue"
  },
  "nationalIdPage": {
    "hasIdCardYesRadioButton": "#hasValidIdCard_true",
    "idCardNumberInput": "#nationalIdCardNo",
    "issuingAuthorityInput": "#issuingAuthority", 
    "issueDayInput": "#issueDate_day",
    "issueMonthInput": "#issueDate_month",
    "issueYearInput": "#issueDate_year",
    "expiryDayInput": "#expiryDate_day",
    "expiryMonthInput": "#expiryDate_month",
    "expiryYearInput": "#expiryDate_year",
    "saveButton": "input#submit.button-continue"
  },
  "nationalityPage": {
    "nationalityInput": "#nationality_ui",
    "countryOfBirthInput": "#countryOfBirth_ui",
    "placeOfBirthInput": "#placeOfBirth",
    "dobDayInput": "#dob_day",
    "dobMonthInput": "#dob_month",
    "dobYearInput": "#dob_year",
    "saveButton": "input#submit.button-continue"
  },
  "otherNationalityPage": {
    "noRadioButton": "#hasOtherNationality_false",
    "saveButton": "input#submit.button-continue"
  },
  "employmentStatusPage": {
    "employedCheckbox": "#status_employed",
    "selfEmployedCheckbox": "#status_self-employed",
    "studentCheckbox": "#status_student",
    "unemployedCheckbox": "#status_unemployed",
    "saveButton": "input#submit.button-continue"
  },
  "employerDetailsPage": {
    "employerInput": "#employer",
    "addressLine1Input": "#address_line1",
    "townCityInput": "#address_townCity",
    "provinceInput": "#address_province",
    "countryInput": "#address_countryRef_ui",
    "phoneCodeInput": "#phone_code",
    "phoneNumberInput": "#phone_number",
    "startDateMonthInput": "#jobStartDate_month",
    "startDateYearInput": "#jobStartDate_year",
    "saveButton": "input#submit.button-continue"
  },
  "jobDetailsPage": {
    "jobTitleInput": "#jobTitle",
    "salaryAmountInput": "#earnings_amount",
    "currencySelect": "#earnings_currencyRef",
    "jobDescriptionTextarea": "#jobDescription",
    "saveButton": "input#submit.button-continue"
  },
  "selfEmployedDetailsPage": {
    "jobTitleInput": "#jobTitle",
    "incomeAmountInput": "#income_amount",
    "currencySelect": "#income_currencyRef",
    "saveButton": "input#submit.button-continue"
  },
  "incomeAndSavingsPage": {
    "moneyInBankCheckbox": "#typeOfIncomeRefs_moneyInBank",
    "currencySelect": "#moneyInBankAmount_currencyRef",
    "amountInput": "#moneyInBankAmount_amount",
    "saveButton": "input#submit.button-continue"
  },
  "visitCostPage": {
    "currencySelect": "#value_currencyRef",
    "amountInput": "#value_amount",
    "saveButton": "input#submit.button-continue"
  },
  "monthlySpendingPage": {
    "currencySelect": "#value_currencyRef",
    "amountInput": "#value_amount",
    "saveButton": "input#submit.button-continue"
  },
  "payingForVisitPage": {
    "yesRadioButton": "#value_true",
    "noRadioButton": "#value_false",
    "saveButton": "input#submit.button-continue"
  },
  "whoIsPayingPage": {
    "someoneIKnowRadio": "#whoIsPayingRef_someoneIKnow",
    "myEmployerRadio": "#whoIsPayingRef_myEmployerOrCompany",
    "otherOrganisationRadio": "#whoIsPayingRef_otherEmployerOrCompany",
    "sponsorNameInput": "#payeeName",
    "addressLine1Input": "#address_line1",
    "townCityInput": "#address_townCity",
    "provinceInput": "#address_province",
    "countryInput": "#address_countryRef_ui",
    "amountInput": "#amount_amount",
    "currencySelect": "#amount_currencyRef",
    "reasonTextarea": "#reason",
    "saveButton": "input#submit.button-continue"
  },
  "addAnotherSponsorPage": {
    "noRadioButton": "#addAnother_false",
    "saveButton": "input#submit.button-continue"
  },
  "travelDatesPage": {
    "arrivalDayInput": "#dateOfArrival_day",
    "arrivalMonthInput": "#dateOfArrival_month",
    "arrivalYearInput": "#dateOfArrival_year",
    "leaveDayInput": "#dateOfLeave_day",
    "leaveMonthInput": "#dateOfLeave_month",
    "leaveYearInput": "#dateOfLeave_year",
    "saveButton": "input#submit.button-continue"
  },
  "languagePreferencePage": {
    "englishRadioButton": "#preferredLanguage_english",
    "saveButton": "input#submit.button-continue"
  },
  "mainPurposePage": {
    "tourismRadioButton": "#purposeRef_tourism",
    "saveButton": "input#submit.button-continue"
  },
  "tourismSubtypePage": {
    "touristRadioButton": "#purposeRef_tourist",
    "saveButton": "input#submit.button-continue"
  },
  "activitiesPage": {
    "detailsTextarea": "#details",
    "saveButton": "input#submit.button-continue"
  },
  "partnerPage": {
    "givenNameInput": "#givenName",
    "familyNameInput": "#familyName",
    "dobDayInput": "#dateOfBirth_day",
    "dobMonthInput": "#dateOfBirth_month",
    "dobYearInput": "#dateOfBirth_year",
    "nationalityInput": "#nationalityRef_ui",
    "liveWithYouYesRadio": "#liveWithYou_true",
    "travellingWithYouYesRadio": "#travellingWithYou_true",
    "passportNumberInput": "#passportNumber",
    "saveButton": "input#submit.button-continue"
  },
  "hasDependantsPage": {
    "yesRadioButton": "#value_true",
    "noRadioButton": "#value_false",
    "saveButton": "input#submit.button-continue"
  },
  "dependantDetailsPage": {
    "relationshipInput": "#relationship",
    "givenNameInput": "#givenName",
    "familyNameInput": "#familyName",
    "dobDayInput": "#dateOfBirth_day",
    "dobMonthInput": "#dateOfBirth_month",
    "dobYearInput": "#dateOfBirth_year",
    "livingWithYouYesRadio": "#livingWithApplicant_true",
    "travellingYesRadio": "#travelling_true",
    "travellingNoRadio": "#travelling_false",
    "nationalityInput": "#nationalityRef_ui",
    "passportNumberInput": "#passportNumber",
    "addAnotherYesRadio": "#addAnother_true",
    "addAnotherNoRadio": "#addAnother_false",
    "saveButton": "input#submit.button-continue"
  },
"parentsPage": {
  "motherRadioButton": "#parent_relationshipRef_mother",
  "fatherRadioButton": "#parent_relationshipRef_father",
  "givenNameInput": "#parent_givenName",
  "familyNameInput": "#parent_familyName",
  "dobDayInput": "#parent_dateOfBirth_day",
  "dobMonthInput": "#parent_dateOfBirth_month",
  "dobYearInput": "#parent_dateOfBirth_year",
  "nationalityInput": "#parent_nationalityRef_ui",
  "sameNationalityYesRadio": "#parent_hadAlwaysSameNationality_true",
  "dontKnowDetailsToggle": "summary[aria-controls='dc_1']",
  "isUnknownCheckbox": "#parentIsUnknown",
  "saveButton": "input#submit.button-continue"
},
"familyInUkPage": {
  "noRadioButton": "#value_false",
  "saveButton": "input#submit.button-continue"
},
"travellingWithOrganisedGroupPage": { 
  "noRadioButton": "#isTravellingWithOtherPeople_false", 
  "saveButton": "input#submit.button-continue"
},
"travellingWithAnyoneElsePage": {
  "noRadioButton": "#isTravellingWithSomeOneNotPartnerOrSpouse_false", 
  "saveButton": "input#submit.button-continue"
},
"accommodationPage": {
  "hasAccommodationYesRadio": "#value_true",
  "saveButton": "input#submit.button-continue"
},
"hotelDetailsPage": {
  "nameInput": "#name",
  "addressLine1Input": "#accommodationDetails_address_line1",
  "townCityInput": "#accommodationDetails_address_townCity",
  "postCodeInput": "#accommodationDetails_address_postCode",
  "checkinDayInput": "#accommodationDetails_dateRange_from_day",
  "checkinMonthInput": "#accommodationDetails_dateRange_from_month",
  "checkinYearInput": "#accommodationDetails_dateRange_from_year",
  "checkoutDayInput": "#accommodationDetails_dateRange_to_day",
  "checkoutMonthInput": "#accommodationDetails_dateRange_to_month",
  "checkoutYearInput": "#accommodationDetails_dateRange_to_year",
  "saveButton": "input#submit.button-continue"
},
"addAnotherAccommodationPage": {
    "noRadioButton": "#addAnother_false",
    "saveButton": "input#submit.button-continue"
  },
  "ukTravelHistoryPage": {
    "yesRadioButton": "#haveBeenToTheUK_true",
    "noRadioButton": "#haveBeenToTheUK_false",
    "numberOfTimesInput": "#numberOfTimes",
    "saveButton": "input#submit.button-continue"
  },
  "previousVisitDetailsPage": {
    "reasonTouristRadio": "#reasonRef_tourist",
    "reasonWorkRadio": "#reasonRef_business",
    "reasonStudyRadio": "#reasonRef_study",
    "reasonTransitRadio": "#reasonRef_transit",
    "reasonOtherRadio": "#reasonRef_other",
    "arrivalMonthInput": "#date_month",
    "arrivalYearInput": "#date_year",
    "durationUnitSelect": "#durationOfStayUnit",
    "durationValueInput": "#durationOfStay",
    "saveButton": "input#submit.button-continue"
  },
  "medicalTreatmentPage": {
    "noRadioButton": "#haveYouHadTreatment_false",
    "saveButton": "input#submit.button-continue"
  },
  "enterAsNationalPage": {
    "noRadioButton": "#value_false",
    "saveButton": "input#submit.button-continue"
  },
  "drivingLicencePage": {
    "noRadioButton": "#doYouHaveADrivingLicence_false",
    "saveButton": "input#submit.button-continue"
  },
  "publicFundsPage": {
    "noRadioButton": "#value_false",
    "saveButton": "input#submit.button-continue"
  },
  "previousVisaPage": {
    "yesRadioButton": "#yesNo_true",
    "noRadioButton": "#yesNo_false",
    "issueMonthInput": "#applicationDetails_dateOfIssue_month",
    "issueYearInput": "#applicationDetails_dateOfIssue_year",
    "saveButton": "input#submit.button-continue"
  },
  "previousApplicationsPage": {
    "noRadioButton": "#previouslyApplied_false",
    "saveButton": "input#submit.button-continue"
  },
  "commonwealthTravelIntroPage": {
    "zeroVisitsRadio": "#bandRef_0",
    "oneVisitRadio": "#bandRef_1",
    "twoToFiveVisitsRadio": "#bandRef_2",
    "sixPlusVisitsRadio": "#bandRef_6",
    "saveButton": "input#submit.button-continue"
  },
  "commonwealthVisitDetailsPage": {
    "australiaRadio": "#countryRef_australia",
    "canadaRadio": "#countryRef_canada",
    "newZealandRadio": "#countryRef_newzealand",
    "usaRadio": "#countryRef_usa",
    "euSwissRadio": "#countryRef_schengen",
    "euCountryInput": "#schengenCountry_ui",
    "reasonTouristRadio": "#reasonRef_tourist",
    "reasonWorkRadio": "#reasonRef_business",
    "reasonStudyRadio": "#reasonRef_study",
    "reasonTransitRadio": "#reasonRef_transit",
    "reasonOtherRadio": "#reasonRef_other",
    "arrivalMonthInput": "#date_month",
    "arrivalYearInput": "#date_year",
    "durationUnitSelect": "#durationOfStayUnit",
    "durationValueInput": "#durationOfStay",
    "saveButton": "input#submit.button-continue"
  },
  "worldTravelIntroPage": {
    "yesRadioButton": "#value_true",
    "noRadioButton": "#value_false",
    "saveButton": "input#submit.button-continue"
  },
  "worldVisitDetailsPage": {
    "countryInput": "#whichCountry_ui",
    "reasonTourismRadio": "#reasonForVisit_tourism",
    "reasonBusinessRadio": "#reasonForVisit_business",
    "reasonStudyRadio": "#reasonForVisit_study",
    "reasonTransitRadio": "#reasonForVisit_transit",
    "reasonOtherRadio": "#reasonForVisit_other",
    "startDateDayInput": "#visitStartDate_day",
    "startDateMonthInput": "#visitStartDate_month",
    "startDateYearInput": "#visitStartDate_year",
    "endDateDayInput": "#visitEndDate_day",
    "endDateMonthInput": "#visitEndDate_month",
    "endDateYearInput": "#visitEndDate_year",
    "saveButton": "input#submit.button-continue"
  },
  "addAnotherWorldVisitPage": {
    "yesRadioButton": "#addAnother_true",
    "noRadioButton": "#addAnother_false",
    "saveButton": "input#submit.button-continue"
  },
  "immigrationHistoryPage": {
    "noRadioButton": "#value_false",
    "saveButton": "input#submit.button-continue"
  },
  "immigrationBreachPage": {
    "noRadioButton": "#value_false",
    "saveButton": "input#submit.button-continue"
  },
  "convictionsPage": {
    "noneRadioButton": "#convictionTypeRef_none",
    "saveButton": "input#submit.button-continue"
  },
  "warCrimesPage": {
    "noRadioButton": "#warCrimesInvolvement_false",
    "confirmCheckbox": "#readAllInfo_iConfirm",
    "saveButton": "input#submit.button-continue"
  },
  "terrorismPage": {
    "activitiesNoRadio": "#terroristActivitiesInvolvement_false",
    "organisationsNoRadio": "#terroristOrganisationsInvolvement_false",
    "viewsNoRadio": "#terroristViewsExpressed_false",
    "confirmCheckbox": "#readAllInfo_iConfirm",
    "saveButton": "input#submit.button-continue"
  },
  "extremismPage": {
    "organisationsNoRadio": "#extremistOrganisationsInvolvement_false",
    "viewsNoRadio": "#extremistViewsExpressed_false",
    "confirmCheckbox": "#readAllInfo_iConfirm",
    "saveButton": "input#submit.button-continue"
  },
  "goodCharacterPage": {
    "goodCharacterNoRadio": "#personOfGoodCharacter_false",
    "otherActivitiesNoRadio": "#otherActivities_false",
    "anyOtherInfoNoRadio": "#anyOtherInfo_false",
    "saveButton": "input#submit.button-continue"
  },
  "employmentHistoryPage": {
    "noneCheckbox": "#none_none",
    "saveButton": "input#submit.button-continue"
  },
  "finalSubmitPage": {
    "saveButton": "input#submit.button-continue"
  }




}